Workbook

Sheet Start Here
B2: Tigrinya Top 1,000 Words — Learning Edition
B3: ትግርኛ ንቈልዑ — Tigrinya for kids of the Eritrean diaspora
B5: What this is | C5: The 1,000 most frequent Tigrinya words found across newspapers, websites, blogs, books and magazines (word list and frequency counts compiled by Fitsum Gaim, MIT). For each word, this edition adds a romanized pronunciation, an English meaning, the kind of word it is, a topic, a learning level, a short example sentence (Tigrinya, romanized, and English), and a learning note written for English-speaking kids and the parents teaching them.
B6: Where to begin | C6: Open the 'Starter Words' tab. It lists the Level 1 words grouped by topic — greetings, family, numbers, question words, and the small grammar words every sentence needs. When those feel easy, use the filter on the 'Word List' tab to show Level 2 (Core) words, and so on.
B7: Reading the sounds | C7: See the 'Pronunciation Guide' tab. Quick version: syllables are split with hyphens (tim-hir-ti); an apostrophe right after t, ts, ch or p means a popped sound (t'i-ray); q is a deep 'k' from the back of the throat; kh is a soft throaty sound like the end of 'Bach'.
B8: Boys, girls, groups | C8: Tigrinya changes many words depending on who you're talking to. Example sentences are marked '(to a boy)', '(to a girl)' or '(to a group)', and the learning notes give the other forms (e.g., ከመይ ኣለኻ? to a boy, ከመይ ኣለኺ? to a girl).
B10: Learning levels
B11: 1 Starter | C11: First words to learn: greetings, family, numbers, question words, everyday nouns, and core grammar words.
B12: 2 Core | C12: Common words for building real sentences and following everyday conversation.
B13: 3 Advanced | C13: Words common in reading — news, stories, school — useful for older kids and teens.
B14: 4 Specialized | C14: Mostly from newspapers (court and legal notices), sports clubs, personal names, religious texts, or split word pieces. Good to recognize; not a priority.
B16: Columns in the Word List
B17: Rank / Tigrinya Word / Frequency | C17: Unchanged from the original list, in the original order. Frequency = number of times the word appeared in the source texts.
B18: Pronunciation | C18: Romanized, kid-friendly spelling split into syllables. See the Pronunciation Guide.
B19: English Meaning | C19: The main meaning(s). Many Tigrinya words cover several English words.
B20: Word Type | C20: Noun, verb form, pointing word (the/this/that), linking word (is/are), and so on.
B21: Topic | C21: One of 21 themes, so you can study related words together (e.g., Time & Calendar, Food & Drink).
B22: Level | C22: 1 Starter → 4 Specialized (see above).
B23: Example (3 columns) | C23: A short sentence or phrase using the word, shown in Tigrinya, in romanized form, and in English.
B24: Learning Note | C24: Grammar tips, related words, male/female/plural forms, and cultural background.
B25: Needs Review | C25: Marked 'Check' where the meaning or usage is uncertain. Please confirm these with a fluent speaker before teaching them.
B27: About the source data
B28: Newspaper legal notices | C28: A large share of the source text comes from court notices in Eritrean newspapers (ሓዳስ ኤርትራ). That is why words like ዝቃወም ('anyone who objects'), ይቕረብ ('let him appear'), ወረስቲ ('heirs') and ይረጋገጸልና ('let it be confirmed for us') rank so high. They are tagged 'Law & Courts' and Level 4.
B29: Religion and sports | C29: Religious publications and European soccer coverage are also well represented — hence የሆዋ (Jehovah), ቸልሲ (Chelsea), ኣርሰናል (Arsenal), and ማን / ሲቲ (pieces of "Man City").
B30: Split forms | C30: About 15 entries aren't full words but pieces split off at apostrophes (ዩ from እዩ, ውን from እውን, ዚ, ቲ, የ, ያ) or softened spellings (ኸም for ከም, ኻብ for ካብ). Each is labeled 'Short / split form' and points to the full word.
B31: Spelling variants | C31: Some words appear more than once with different spellings (ኮይኑ / ኰይኑ / ዀይኑ, ኩሉ / ኵሉ / ዅሉ, ተመሃሮ / ተማሃሮ). The learning notes cross-reference them.
B32: Order | C32: The original order was kept. In a few places neighboring rows are slightly out of frequency order in the source (e.g., ranks 110 and 111).
B34: Please note | C34: The pronunciations, translations, and example sentences were written for learners and checked for consistency with the Ge'ez spelling, but they have not been reviewed by a native speaker. Before using this with children, have a fluent Tigrinya speaker look over the examples (especially rows marked 'Check'), since phrasing and word choice can vary by region and family.
B36: Credit | C36: Original word list and frequencies: Fitsum Gaim (MIT). Learning data added in this edition.

Sheet Starter Words
A1: Starter Words — the first words to learn, grouped by topic
A2: Every cell links back to the Word List, so edits there show up here. Words are in frequency order within each topic.
A4: Topic | B4: Rank | C4: Tigrinya | D4: Pronunciation | E4: English Meaning | F4: Example (Tigrinya) | G4: Example (Romanized) | H4: Example (English)
A5: ='Word List'!G2 -> Grammar Essentials | B5: ='Word List'!A2 -> 1 | C5: ='Word List'!B2 -> ኣብ | D5: ='Word List'!D2 -> ab | E5: ='Word List'!E2 -> at, in, on | F5: ='Word List'!I2 -> ኣብ ገዛ ኣለኹ። | G5: ='Word List'!J2 -> ab geza allekhu. | H5: ='Word List'!K2 -> I am at home.
A6: ='Word List'!G3 -> Grammar Essentials | B6: ='Word List'!A3 -> 2 | C6: ='Word List'!B3 -> ናይ | D6: ='Word List'!D3 -> nay | E6: ='Word List'!E3 -> of; belonging to ('s) | F6: ='Word List'!I3 -> ናይ ኣደይ መኪና | G6: ='Word List'!J3 -> nay adey mekina | H6: ='Word List'!K3 -> my mother's car
A7: ='Word List'!G4 -> Grammar Essentials | B7: ='Word List'!A4 -> 3 | C7: ='Word List'!B4 -> እዩ | D7: ='Word List'!D4 -> i-yu | E7: ='Word List'!E4 -> is (he/it is) | F7: ='Word List'!I4 -> እዚ ማይ እዩ። | G7: ='Word List'!J4 -> izi may iyu. | H7: ='Word List'!K4 -> This is water.
A8: ='Word List'!G5 -> Grammar Essentials | B8: ='Word List'!A5 -> 4 | C8: ='Word List'!B5 -> ካብ | D8: ='Word List'!D5 -> kab | E8: ='Word List'!E5 -> from | F8: ='Word List'!I5 -> ካብ ኣስመራ እየ። | G8: ='Word List'!J5 -> kab asmera iye. | H8: ='Word List'!K5 -> I am from Asmara.
A9: ='Word List'!G6 -> Grammar Essentials | B9: ='Word List'!A6 -> 5 | C9: ='Word List'!B6 -> ከም | D9: ='Word List'!D6 -> kem | E9: ='Word List'!E6 -> like, as | F9: ='Word List'!I6 -> ከም ኣቦኻ ኢኻ። | G9: ='Word List'!J6 -> kem abokha ikha. | H9: ='Word List'!K6 -> You are like your father.
A10: ='Word List'!G7 -> Grammar Essentials | B10: ='Word List'!A7 -> 6 | C10: ='Word List'!B7 -> እቲ | D10: ='Word List'!D7 -> i-ti | E10: ='Word List'!E7 -> the; that (masculine) | F10: ='Word List'!I7 -> እቲ ቈልዓ ይጻወት ኣሎ። | G10: ='Word List'!J7 -> iti qol'a yits'awet allo. | H10: ='Word List'!K7 -> The child is playing.
A11: ='Word List'!G8 -> Grammar Essentials | B11: ='Word List'!A8 -> 7 | C11: ='Word List'!B8 -> ድማ | D11: ='Word List'!D8 -> dim-ma | E11: ='Word List'!E8 -> and; also | F11: ='Word List'!I8 -> ኣነ ድማ ክመጽእ እየ። | G11: ='Word List'!J8 -> ane dimma kimets'i iye. | H11: ='Word List'!K8 -> And I will come too.
A12: ='Word List'!G9 -> Grammar Essentials | B12: ='Word List'!A9 -> 8 | C12: ='Word List'!B9 -> ምስ | D12: ='Word List'!D9 -> mis | E12: ='Word List'!E9 -> with | F12: ='Word List'!I9 -> ምስ ኣደይ ከይደ። | G12: ='Word List'!J9 -> mis adey keyde. | H12: ='Word List'!K9 -> I went with my mother.
A13: ='Word List'!G10 -> Grammar Essentials | B13: ='Word List'!A10 -> 9 | C13: ='Word List'!B10 -> ናብ | D13: ='Word List'!D10 -> nab | E13: ='Word List'!E10 -> to, toward | F13: ='Word List'!I10 -> ናብ ቤት ትምህርቲ ንኸይድ ኣለና። | G13: ='Word List'!J10 -> nab bet timhirti nikheyd allena. | H13: ='Word List'!K10 -> We are going to school.
A14: ='Word List'!G11 -> Grammar Essentials | B14: ='Word List'!A11 -> 10 | C14: ='Word List'!B11 -> እዚ | D14: ='Word List'!D11 -> i-zi | E14: ='Word List'!E11 -> this (masculine) | F14: ='Word List'!I11 -> እዚ እንታይ እዩ? | G14: ='Word List'!J11 -> izi intay iyu? | H14: ='Word List'!K11 -> What is this?
A15: ='Word List'!G15 -> Grammar Essentials | B15: ='Word List'!A15 -> 14 | C15: ='Word List'!B15 -> ከኣ | D15: ='Word List'!D15 -> ke-a | E15: ='Word List'!E15 -> and; also | F15: ='Word List'!I15 -> ንሳ ከኣ መጺኣ። | G15: ='Word List'!J15 -> nisa ke'a mets'i'a. | H15: ='Word List'!K15 -> And she came too.
A16: ='Word List'!G17 -> Grammar Essentials | B16: ='Word List'!A17 -> 16 | C16: ='Word List'!B17 -> ግን | D16: ='Word List'!D17 -> gin | E16: ='Word List'!E17 -> but | F16: ='Word List'!I17 -> ደኺመ ግን ሕጉስ እየ። | G16: ='Word List'!J17 -> dekhime gin higus iye. | H16: ='Word List'!K17 -> I'm tired, but I'm happy.
A17: ='Word List'!G19 -> Grammar Essentials | B17: ='Word List'!A19 -> 18 | C17: ='Word List'!B19 -> ወይ | D17: ='Word List'!D19 -> wey | E17: ='Word List'!E19 -> or | F17: ='Word List'!I19 -> ሻሂ ወይ ቡን? | G17: ='Word List'!J19 -> shahi wey bun? | H17: ='Word List'!K19 -> Tea or coffee?
A18: ='Word List'!G20 -> Grammar Essentials | B18: ='Word List'!A20 -> 19 | C18: ='Word List'!B20 -> እውን | D18: ='Word List'!D20 -> i-wun | E18: ='Word List'!E20 -> also, too | F18: ='Word List'!I20 -> ኣነ እውን ክመጽእ እየ። | G18: ='Word List'!J20 -> ane iwun kimets'i iye. | H18: ='Word List'!K20 -> I will come too.
A19: ='Word List'!G28 -> Grammar Essentials | B19: ='Word List'!A28 -> 27 | C19: ='Word List'!B28 -> እዮም | D19: ='Word List'!D28 -> i-yom | E19: ='Word List'!E28 -> are (they are) | F19: ='Word List'!I28 -> ንሳቶም ኣሕዋተይ እዮም። | G19: ='Word List'!J28 -> nisatom ahwatey iyom. | H19: ='Word List'!K28 -> They are my brothers.
A20: ='Word List'!G34 -> Grammar Essentials | B20: ='Word List'!A34 -> 33 | C20: ='Word List'!B34 -> ኣሎ | D20: ='Word List'!D34 -> al-lo | E20: ='Word List'!E34 -> there is; he/it is (here) | F20: ='Word List'!I34 -> ማይ ኣሎ ድዩ? | G20: ='Word List'!J34 -> may allo diyu? | H20: ='Word List'!K34 -> Is there water?
A21: ='Word List'!G40 -> Grammar Essentials | B21: ='Word List'!A40 -> 39 | C21: ='Word List'!B40 -> እታ | D21: ='Word List'!D40 -> i-ta | E21: ='Word List'!E40 -> the; that (feminine) | F21: ='Word List'!I40 -> እታ ጓል | G21: ='Word List'!J40 -> ita gwal | H21: ='Word List'!K40 -> the girl
A22: ='Word List'!G55 -> Grammar Essentials | B22: ='Word List'!A55 -> 54 | C22: ='Word List'!B55 -> ኢና | D22: ='Word List'!D55 -> i-na | E22: ='Word List'!E55 -> are (we are) | F22: ='Word List'!I55 -> ኤርትራውያን ኢና። | G22: ='Word List'!J55 -> ertrawyan ina. | H22: ='Word List'!K55 -> We are Eritreans.
A23: ='Word List'!G57 -> Grammar Essentials | B23: ='Word List'!A57 -> 56 | C23: ='Word List'!B57 -> ኣብዚ | D23: ='Word List'!D57 -> ab-zi | E23: ='Word List'!E57 -> here; in this | F23: ='Word List'!I57 -> ኣብዚ ተቐመጥ። | G23: ='Word List'!J57 -> abzi teqemet'. | H23: ='Word List'!K57 -> Sit here. (to a boy)
A24: ='Word List'!G58 -> Grammar Essentials | B24: ='Word List'!A58 -> 57 | C24: ='Word List'!B58 -> እያ | D24: ='Word List'!D58 -> i-ya | E24: ='Word List'!E58 -> is (she is) | F24: ='Word List'!I58 -> ንሳ ሓብተይ እያ። | G24: ='Word List'!J58 -> nisa habtey iya. | H24: ='Word List'!K58 -> She is my sister.
A25: ='Word List'!G62 -> Grammar Essentials | B25: ='Word List'!A62 -> 61 | C25: ='Word List'!B62 -> ኣነ | D25: ='Word List'!D62 -> a-ne | E25: ='Word List'!E62 -> I; me | F25: ='Word List'!I62 -> ኣነ ሳባ እየ። | G25: ='Word List'!J62 -> ane saba iye. | H25: ='Word List'!K62 -> I am Saba.
A26: ='Word List'!G63 -> Grammar Essentials | B26: ='Word List'!A63 -> 62 | C26: ='Word List'!B63 -> እየ | D26: ='Word List'!D63 -> i-ye | E26: ='Word List'!E63 -> am (I am) | F26: ='Word List'!I63 -> ደሓን እየ። | G26: ='Word List'!J63 -> dehan iye. | H26: ='Word List'!K63 -> I am fine.
A27: ='Word List'!G107 -> Grammar Essentials | B27: ='Word List'!A107 -> 106 | C27: ='Word List'!B107 -> ንሱ | D27: ='Word List'!D107 -> ni-su | E27: ='Word List'!E107 -> he; him | F27: ='Word List'!I107 -> ንሱ ሓወይ እዩ። | G27: ='Word List'!J107 -> nisu hawey iyu. | H27: ='Word List'!K107 -> He is my brother.
A28: ='Word List'!G110 -> Grammar Essentials | B28: ='Word List'!A110 -> 109 | C28: ='Word List'!B110 -> ከምዚ | D28: ='Word List'!D110 -> kem-zi | E28: ='Word List'!E110 -> like this; this way | F28: ='Word List'!I110 -> ከምዚ ግበር። | G28: ='Word List'!J110 -> kemzi giber. | H28: ='Word List'!K110 -> Do it like this. (to a boy)
A29: ='Word List'!G126 -> Grammar Essentials | B29: ='Word List'!A126 -> 125 | C29: ='Word List'!B126 -> ኣለዎ | D29: ='Word List'!D126 -> al-le-wo | E29: ='Word List'!E126 -> he/it has | F29: ='Word List'!I126 -> ንሱ ድሙ ኣለዎ። | G29: ='Word List'!J126 -> nisu dimmu allewo. | H29: ='Word List'!K126 -> He has a cat.
A30: ='Word List'!G130 -> Grammar Essentials | B30: ='Word List'!A130 -> 129 | C30: ='Word List'!B130 -> ኢኻ | D30: ='Word List'!D130 -> i-kha | E30: ='Word List'!E130 -> are (you are, to a boy/man) | F30: ='Word List'!I130 -> ጐበዝ ኢኻ! | G30: ='Word List'!J130 -> gobez ikha! | H30: ='Word List'!K130 -> You're great! / Well done! (to a boy)
A31: ='Word List'!G157 -> Grammar Essentials | B31: ='Word List'!A157 -> 156 | C31: ='Word List'!B157 -> ውሽጢ | D31: ='Word List'!D157 -> wish-t'i | E31: ='Word List'!E157 -> inside | F31: ='Word List'!I157 -> ኣብ ውሽጢ ገዛ | G31: ='Word List'!J157 -> ab wisht'i geza | H31: ='Word List'!K157 -> inside the house
A32: ='Word List'!G178 -> Grammar Essentials | B32: ='Word List'!A178 -> 177 | C32: ='Word List'!B178 -> እዛ | D32: ='Word List'!D178 -> i-za | E32: ='Word List'!E178 -> this (feminine) | F32: ='Word List'!I178 -> እዛ ጓል ሓብተይ እያ። | G32: ='Word List'!J178 -> iza gwal habtey iya. | H32: ='Word List'!K178 -> This girl is my sister.
A33: ='Word List'!G189 -> Grammar Essentials | B33: ='Word List'!A189 -> 188 | C33: ='Word List'!B189 -> ትሕቲ | D33: ='Word List'!D189 -> tih-ti | E33: ='Word List'!E189 -> under; below | F33: ='Word List'!I189 -> ኣብ ትሕቲ ጠረጴዛ | G33: ='Word List'!J189 -> ab tihti t'erep'eza | H33: ='Word List'!K189 -> under the table
A34: ='Word List'!G195 -> Grammar Essentials | B34: ='Word List'!A195 -> 194 | C34: ='Word List'!B195 -> ኣለዉ | D34: ='Word List'!D195 -> al-le-wu | E34: ='Word List'!E195 -> they are (here); there are | F34: ='Word List'!I195 -> ኣሕዋተይ ኣብ ገዛ ኣለዉ። | G34: ='Word List'!J195 -> ahwatey ab geza allewu. | H34: ='Word List'!K195 -> My brothers are at home.
A35: ='Word List'!G204 -> Grammar Essentials | B35: ='Word List'!A204 -> 203 | C35: ='Word List'!B204 -> ኣይኮነን | D35: ='Word List'!D204 -> ay-ko-nen | E35: ='Word List'!E204 -> is not; no, it isn't | F35: ='Word List'!I204 -> እዚ ናተይ ኣይኮነን። | G35: ='Word List'!J204 -> izi natey aykonen. | H35: ='Word List'!K204 -> This is not mine.
A36: ='Word List'!G243 -> Grammar Essentials | B36: ='Word List'!A243 -> 242 | C36: ='Word List'!B243 -> ንዓይ | D36: ='Word List'!D243 -> ni-ay | E36: ='Word List'!E243 -> me; to me; for me | F36: ='Word List'!I243 -> ንዓይ ሃበኒ። | G36: ='Word List'!J243 -> ni'ay habeni. | H36: ='Word List'!K243 -> Give it to me. (to a boy)
A37: ='Word List'!G261 -> Grammar Essentials | B37: ='Word List'!A261 -> 260 | C37: ='Word List'!B261 -> ምኽንያቱ | D37: ='Word List'!D261 -> mikh-ni-ya-tu | E37: ='Word List'!E261 -> because | F37: ='Word List'!I261 -> ኣይመጻእኩን፡ ምኽንያቱ ሓሚመ ነይረ። | G37: ='Word List'!J261 -> aymets'a'kun, mikhniyatu hamime neyre. | H37: ='Word List'!K261 -> I didn't come because I was sick.
A38: ='Word List'!G267 -> Grammar Essentials | B38: ='Word List'!A267 -> 266 | C38: ='Word List'!B267 -> ኣለኹ | D38: ='Word List'!D267 -> al-le-khu | E38: ='Word List'!E267 -> I am (here); I am (doing) | F38: ='Word List'!I267 -> ኣብዚ ኣለኹ! | G38: ='Word List'!J267 -> abzi allekhu! | H38: ='Word List'!K267 -> I'm here!
A39: ='Word List'!G318 -> Grammar Essentials | B39: ='Word List'!A318 -> 317 | C39: ='Word List'!B318 -> የለን | D39: ='Word List'!D318 -> ye-len | E39: ='Word List'!E318 -> there isn't; no; is not here | F39: ='Word List'!I318 -> ኣቦይ ኣብ ገዛ የለን። | G39: ='Word List'!J318 -> aboy ab geza yelen. | H39: ='Word List'!K318 -> My dad isn't home.
A40: ='Word List'!G327 -> Grammar Essentials | B40: ='Word List'!A327 -> 326 | C40: ='Word List'!B327 -> ንሕና | D40: ='Word List'!D327 -> nih-na | E40: ='Word List'!E327 -> we; us | F40: ='Word List'!I327 -> ንሕና ኤርትራውያን ኢና። | G40: ='Word List'!J327 -> nihna ertrawyan ina. | H40: ='Word List'!K327 -> We are Eritreans.
A41: ='Word List'!G339 -> Grammar Essentials | B41: ='Word List'!A339 -> 338 | C41: ='Word List'!B339 -> ኣብኡ | D41: ='Word List'!D339 -> ab-u | E41: ='Word List'!E339 -> there; in it | F41: ='Word List'!I339 -> ኣብኡ ኣሎ። | G41: ='Word List'!J339 -> ab'u allo. | H41: ='Word List'!K339 -> It's there.
A42: ='Word List'!G354 -> Grammar Essentials | B42: ='Word List'!A354 -> 353 | C42: ='Word List'!B354 -> ኣላ | D42: ='Word List'!D354 -> al-la | E42: ='Word List'!E354 -> she is (here); there is (feminine) | F42: ='Word List'!I354 -> ኣደይ ኣብ ገዛ ኣላ። | G42: ='Word List'!J354 -> adey ab geza alla. | H42: ='Word List'!K354 -> My mom is at home.
A43: ='Word List'!G370 -> Grammar Essentials | B43: ='Word List'!A370 -> 369 | C43: ='Word List'!B370 -> ንስኻ | D43: ='Word List'!D370 -> nis-kha | E43: ='Word List'!E370 -> you (to a boy/man) | F43: ='Word List'!I370 -> ንስኻኸ? | G43: ='Word List'!J370 -> niskhakhe? | H43: ='Word List'!K370 -> And you? / What about you? (to a boy)
A44: ='Word List'!G403 -> Grammar Essentials | B44: ='Word List'!A403 -> 402 | C44: ='Word List'!B403 -> ኣለና | D44: ='Word List'!D403 -> al-le-na | E44: ='Word List'!E403 -> we are (here) | F44: ='Word List'!I403 -> ኣብ ገዛ ኣለና። | G44: ='Word List'!J403 -> ab geza allena. | H44: ='Word List'!K403 -> We are at home.
A45: ='Word List'!G432 -> Grammar Essentials | B45: ='Word List'!A432 -> 431 | C45: ='Word List'!B432 -> ንሳ | D45: ='Word List'!D432 -> ni-sa | E45: ='Word List'!E432 -> she; her | F45: ='Word List'!I432 -> ንሳ ኣደይ እያ። | G45: ='Word List'!J432 -> nisa adey iya. | H45: ='Word List'!K432 -> She is my mother.
A46: ='Word List'!G447 -> Grammar Essentials | B46: ='Word List'!A447 -> 446 | C46: ='Word List'!B447 -> ኩሎም | D46: ='Word List'!D447 -> kul-lom | E46: ='Word List'!E447 -> all of them; everyone | F46: ='Word List'!I447 -> ኩሎም መጺኦም። | G46: ='Word List'!J447 -> kullom mets'i'om. | H46: ='Word List'!K447 -> Everyone came.
A47: ='Word List'!G451 -> Grammar Essentials | B47: ='Word List'!A451 -> 450 | C47: ='Word List'!B451 -> ንሳቶም | D47: ='Word List'!D451 -> ni-sa-tom | E47: ='Word List'!E451 -> they; them | F47: ='Word List'!I451 -> ንሳቶም ኣዕሩኸይ እዮም። | G47: ='Word List'!J451 -> nisatom a'rukhey iyom. | H47: ='Word List'!K451 -> They are my friends.
A48: ='Word List'!G518 -> Grammar Essentials | B48: ='Word List'!A518 -> 517 | C48: ='Word List'!B518 -> እወ | D48: ='Word List'!D518 -> i-we | E48: ='Word List'!E518 -> yes | F48: ='Word List'!I518 -> እወ፡ ደሓን እየ። | G48: ='Word List'!J518 -> iwe, dehan iye. | H48: ='Word List'!K518 -> Yes, I'm fine.
A49: ='Word List'!G636 -> Grammar Essentials | B49: ='Word List'!A636 -> 635 | C49: ='Word List'!B636 -> ኣሎና | D49: ='Word List'!D636 -> al-lo-na | E49: ='Word List'!E636 -> we have | F49: ='Word List'!I636 -> ሓደ ድሙ ኣሎና። | G49: ='Word List'!J636 -> hade dimmu allona. | H49: ='Word List'!K636 -> We have a cat.
A50: ='Word List'!G714 -> Grammar Essentials | B50: ='Word List'!A714 -> 713 | C50: ='Word List'!B714 -> ኢኺ | D50: ='Word List'!D714 -> i-khi | E50: ='Word List'!E714 -> are (you are, to a girl/woman) | F50: ='Word List'!I714 -> ጐባዝ ኢኺ! | G50: ='Word List'!J714 -> gobaz ikhi! | H50: ='Word List'!K714 -> You're great! (to a girl)
A51: ='Word List'!G743 -> Grammar Essentials | B51: ='Word List'!A743 -> 742 | C51: ='Word List'!B743 -> ኢኹም | D51: ='Word List'!D743 -> i-khum | E51: ='Word List'!E743 -> are (you are, to a group) | F51: ='Word List'!I743 -> ጐበዛት ኢኹም! | G51: ='Word List'!J743 -> gobezat ikhum! | H51: ='Word List'!K743 -> You're all great!
A52: ='Word List'!G759 -> Grammar Essentials | B52: ='Word List'!A759 -> 758 | C52: ='Word List'!B759 -> ብሓባር | D52: ='Word List'!D759 -> bi-ha-bar | E52: ='Word List'!E759 -> together | F52: ='Word List'!I759 -> ብሓባር ንጻወት። | G52: ='Word List'!J759 -> bihabar nits'awet. | H52: ='Word List'!K759 -> Let's play together.
A53: ='Word List'!G867 -> Grammar Essentials | B53: ='Word List'!A867 -> 866 | C53: ='Word List'!B867 -> ንዕኡ | D53: ='Word List'!D867 -> ni-'i-'u | E53: ='Word List'!E867 -> him; to him | F53: ='Word List'!I867 -> ንዕኡ ሃቦ። | G53: ='Word List'!J867 -> ni'i'u habo. | H53: ='Word List'!K867 -> Give it to him. (to a boy)
A54: ='Word List'!G32 -> Questions | B54: ='Word List'!A32 -> 31 | C54: ='Word List'!B32 -> እንታይ | D54: ='Word List'!D32 -> in-tay | E54: ='Word List'!E32 -> what? | F54: ='Word List'!I32 -> እንታይ ትደሊ? | G54: ='Word List'!J32 -> intay tideli? | H54: ='Word List'!K32 -> What do you want? (to a boy)
A55: ='Word List'!G174 -> Questions | B55: ='Word List'!A174 -> 173 | C55: ='Word List'!B174 -> ከመይ | D55: ='Word List'!D174 -> ke-mey | E55: ='Word List'!E174 -> how? | F55: ='Word List'!I174 -> ከመይ ኣለኻ? | G55: ='Word List'!J174 -> kemey allekha? | H55: ='Word List'!K174 -> How are you? (to a boy/man)
A56: ='Word List'!G197 -> Questions | B56: ='Word List'!A197 -> 196 | C56: ='Word List'!B197 -> ስለምንታይ | D56: ='Word List'!D197 -> si-le-min-tay | E56: ='Word List'!E197 -> why? | F56: ='Word List'!I197 -> ስለምንታይ ዘይመጻእካ? | G56: ='Word List'!J197 -> silemintay zeymets'a'ka? | H56: ='Word List'!K197 -> Why didn't you come? (to a boy)
A57: ='Word List'!G248 -> Questions | B57: ='Word List'!A248 -> 247 | C57: ='Word List'!B248 -> ድዩ | D57: ='Word List'!D248 -> di-yu | E57: ='Word List'!E248 -> is it? (question form) | F57: ='Word List'!I248 -> ጽቡቕ ድዩ? | G57: ='Word List'!J248 -> ts'ibuq diyu? | H57: ='Word List'!K248 -> Is it good?
A58: ='Word List'!G277 -> Questions | B58: ='Word List'!A277 -> 276 | C58: ='Word List'!B277 -> መን | D58: ='Word List'!D277 -> men | E58: ='Word List'!E277 -> who? | F58: ='Word List'!I277 -> መን እዩ? | G58: ='Word List'!J277 -> men iyu? | H58: ='Word List'!K277 -> Who is it?
A59: ='Word List'!G313 -> Questions | B59: ='Word List'!A313 -> 312 | C59: ='Word List'!B313 -> ክንደይ | D59: ='Word List'!D313 -> kin-dey | E59: ='Word List'!E313 -> how much? how many? | F59: ='Word List'!I313 -> ክንደይ እዩ? | G59: ='Word List'!J313 -> kindey iyu? | H59: ='Word List'!K313 -> How much is it?
A60: ='Word List'!G586 -> Questions | B60: ='Word List'!A586 -> 585 | C60: ='Word List'!B586 -> መዓስ | D60: ='Word List'!D586 -> me-as | E60: ='Word List'!E586 -> when? | F60: ='Word List'!I586 -> መዓስ ትመጽእ? | G60: ='Word List'!J586 -> me'as timets'i'? | H60: ='Word List'!K586 -> When are you coming? (to a boy)
A61: ='Word List'!G678 -> Questions | B61: ='Word List'!A678 -> 677 | C61: ='Word List'!B678 -> ኣበይ | D61: ='Word List'!D678 -> a-bey | E61: ='Word List'!E678 -> where? | F61: ='Word List'!I678 -> ኣበይ ኣለኻ? | G61: ='Word List'!J678 -> abey allekha? | H61: ='Word List'!K678 -> Where are you? (to a boy)
A62: ='Word List'!G956 -> Questions | B62: ='Word List'!A956 -> 955 | C62: ='Word List'!B956 -> ዲኻ | D62: ='Word List'!D956 -> di-kha | E62: ='Word List'!E956 -> are you? (to a boy) | F62: ='Word List'!I956 -> ደሓን ዲኻ? | G62: ='Word List'!J956 -> dehan dikha? | H62: ='Word List'!K956 -> Are you OK? (to a boy)
A63: ='Word List'!G18 -> People & Family | B63: ='Word List'!A18 -> 17 | C63: ='Word List'!B18 -> ሰብ | D63: ='Word List'!D18 -> seb | E63: ='Word List'!E18 -> person | F63: ='Word List'!I18 -> ጽቡቕ ሰብ እዩ። | G63: ='Word List'!J18 -> ts'ibuq seb iyu. | H63: ='Word List'!K18 -> He is a good person.
A64: ='Word List'!G30 -> People & Family | B64: ='Word List'!A30 -> 29 | C64: ='Word List'!B30 -> ሰባት | D64: ='Word List'!D30 -> se-bat | E64: ='Word List'!E30 -> people | F64: ='Word List'!I30 -> ብዙሓት ሰባት መጺኦም። | G64: ='Word List'!J30 -> bizuhat sebat mets'i'om. | H64: ='Word List'!K30 -> Many people came.
A65: ='Word List'!G89 -> People & Family | B65: ='Word List'!A89 -> 88 | C65: ='Word List'!B89 -> ወዲ | D65: ='Word List'!D89 -> we-di | E65: ='Word List'!E89 -> son; boy | F65: ='Word List'!I89 -> ወዲ ሸውዓተ ዓመት | G65: ='Word List'!J89 -> wedi shew'ate amet | H65: ='Word List'!K89 -> a seven-year-old boy
A66: ='Word List'!G238 -> People & Family | B66: ='Word List'!A238 -> 237 | C66: ='Word List'!B238 -> ስም | D66: ='Word List'!D238 -> sim | E66: ='Word List'!E238 -> name | F66: ='Word List'!I238 -> ስመይ ሳባ እዩ። | G66: ='Word List'!J238 -> simey saba iyu. | H66: ='Word List'!K238 -> My name is Saba.
A67: ='Word List'!G259 -> People & Family | B67: ='Word List'!A259 -> 258 | C67: ='Word List'!B259 -> ጓል | D67: ='Word List'!D259 -> gwal | E67: ='Word List'!E259 -> girl; daughter | F67: ='Word List'!I259 -> ጓለይ | G67: ='Word List'!J259 -> gwaley | H67: ='Word List'!K259 -> my daughter
A68: ='Word List'!G303 -> People & Family | B68: ='Word List'!A303 -> 302 | C68: ='Word List'!B303 -> ስድራ | D68: ='Word List'!D303 -> sid-ra | E68: ='Word List'!E303 -> family | F68: ='Word List'!I303 -> ስድራይ ኣብ ኣመሪካ ይነብሩ። | G68: ='Word List'!J303 -> sidray ab amerika yinebru. | H68: ='Word List'!K303 -> My family lives in America.
A69: ='Word List'!G388 -> People & Family | B69: ='Word List'!A388 -> 387 | C69: ='Word List'!B388 -> ሰብኣይ | D69: ='Word List'!D388 -> seb-ay | E69: ='Word List'!E388 -> man; husband | F69: ='Word List'!I388 -> ነዊሕ ሰብኣይ | G69: ='Word List'!J388 -> newih seb'ay | H69: ='Word List'!K388 -> a tall man
A70: ='Word List'!G400 -> People & Family | B70: ='Word List'!A400 -> 399 | C70: ='Word List'!B400 -> ኣቦ | D70: ='Word List'!D400 -> a-bo | E70: ='Word List'!E400 -> father | F70: ='Word List'!I400 -> ኣቦይ | G70: ='Word List'!J400 -> aboy | H70: ='Word List'!K400 -> my father; Dad
A71: ='Word List'!G405 -> People & Family | B71: ='Word List'!A405 -> 404 | C71: ='Word List'!B405 -> ኤርትራውያን | D71: ='Word List'!D405 -> er-tra-wi-yan | E71: ='Word List'!E405 -> Eritreans | F71: ='Word List'!I405 -> ንሕና ኤርትራውያን ኢና። | G71: ='Word List'!J405 -> nihna ertrawiyan ina. | H71: ='Word List'!K405 -> We are Eritreans.
A72: ='Word List'!G562 -> People & Family | B72: ='Word List'!A562 -> 561 | C72: ='Word List'!B562 -> ኣደ | D72: ='Word List'!D562 -> a-de | E72: ='Word List'!E562 -> mother | F72: ='Word List'!I562 -> ኣደይ | G72: ='Word List'!J562 -> adey | H72: ='Word List'!K562 -> my mother; Mom
A73: ='Word List'!G569 -> People & Family | B73: ='Word List'!A569 -> 568 | C73: ='Word List'!B569 -> ቈልዑ | D73: ='Word List'!D569 -> qol-u | E73: ='Word List'!E569 -> children; kids | F73: ='Word List'!I569 -> ቈልዑ ይጻወቱ ኣለዉ። | G73: ='Word List'!J569 -> qol'u yits'awetu allewu. | H73: ='Word List'!K569 -> The kids are playing.
A74: ='Word List'!G595 -> People & Family | B74: ='Word List'!A595 -> 594 | C74: ='Word List'!B595 -> ሰበይቲ | D74: ='Word List'!D595 -> se-bey-ti | E74: ='Word List'!E595 -> woman; wife | F74: ='Word List'!I595 -> ሰበይቲ ኣቶ ተስፋይ | G74: ='Word List'!J595 -> sebeyti ato tesfay | H74: ='Word List'!K595 -> Mr. Tesfay's wife
A75: ='Word List'!G647 -> People & Family | B75: ='Word List'!A647 -> 646 | C75: ='Word List'!B647 -> ወለዲ | D75: ='Word List'!D647 -> we-le-di | E75: ='Word List'!E647 -> parents | F75: ='Word List'!I647 -> ወለደይ | G75: ='Word List'!J647 -> weledey | H75: ='Word List'!K647 -> my parents
A76: ='Word List'!G653 -> People & Family | B76: ='Word List'!A653 -> 652 | C76: ='Word List'!B653 -> ኣደይ | D76: ='Word List'!D653 -> a-dey | E76: ='Word List'!E653 -> my mother; Mom | F76: ='Word List'!I653 -> ኣደይ፡ የፍቕረኪ እየ። | G76: ='Word List'!J653 -> adey, yefqireki iye. | H76: ='Word List'!K653 -> Mom, I love you.
A77: ='Word List'!G681 -> People & Family | B77: ='Word List'!A681 -> 680 | C77: ='Word List'!B681 -> ኣቦይ | D77: ='Word List'!D681 -> a-boy | E77: ='Word List'!E681 -> my father; Dad | F77: ='Word List'!I681 -> ኣቦይ ኣብ ስራሕ ኣሎ። | G77: ='Word List'!J681 -> aboy ab sirah allo. | H77: ='Word List'!K681 -> Dad is at work.
A78: ='Word List'!G722 -> People & Family | B78: ='Word List'!A722 -> 721 | C78: ='Word List'!B722 -> ኣሕዋተይ | D78: ='Word List'!D722 -> ah-wa-tey | E78: ='Word List'!E722 -> my brothers; my siblings | F78: ='Word List'!I722 -> ኣሕዋተይ ይፈትዉኒ። | G78: ='Word List'!J722 -> ahwatey yifetwuni. | H78: ='Word List'!K722 -> My brothers love me.
A79: ='Word List'!G787 -> People & Family | B79: ='Word List'!A787 -> 786 | C79: ='Word List'!B787 -> ቈልዓ | D79: ='Word List'!D787 -> qol-a | E79: ='Word List'!E787 -> child; kid | F79: ='Word List'!I787 -> ጐበዝ ቈልዓ | G79: ='Word List'!J787 -> gobez qol'a | H79: ='Word List'!K787 -> a good kid
A80: ='Word List'!G794 -> People & Family | B80: ='Word List'!A794 -> 793 | C80: ='Word List'!B794 -> ስድራቤት | D80: ='Word List'!D794 -> sid-ra-bet | E80: ='Word List'!E794 -> family; household | F80: ='Word List'!I794 -> ስድራቤትና | G80: ='Word List'!J794 -> sidrabetna | H80: ='Word List'!K794 -> our family
A81: ='Word List'!G904 -> People & Family | B81: ='Word List'!A904 -> 903 | C81: ='Word List'!B904 -> ህጻን | D81: ='Word List'!D904 -> hi-ts'an | E81: ='Word List'!E904 -> baby; infant | F81: ='Word List'!I904 -> ንእሽቶ ህጻን | G81: ='Word List'!J904 -> ni'ishto hits'an | H81: ='Word List'!K904 -> a little baby
A82: ='Word List'!G14 -> Numbers & Amounts | B82: ='Word List'!A14 -> 13 | C82: ='Word List'!B14 -> ሓደ | D82: ='Word List'!D14 -> ha-de | E82: ='Word List'!E14 -> one (masculine); a, an | F82: ='Word List'!I14 -> ሓደ ቈልዓ | G82: ='Word List'!J14 -> hade qol'a | H82: ='Word List'!K14 -> one child; a child
A83: ='Word List'!G70 -> Numbers & Amounts | B83: ='Word List'!A70 -> 69 | C83: ='Word List'!B70 -> ክልተ | D83: ='Word List'!D70 -> kil-te | E83: ='Word List'!E70 -> two | F83: ='Word List'!I70 -> ክልተ ኣዒንቲ | G83: ='Word List'!J70 -> kilte a'inti | H83: ='Word List'!K70 -> two eyes
A84: ='Word List'!G91 -> Numbers & Amounts | B84: ='Word List'!A91 -> 90 | C84: ='Word List'!B91 -> ሓንቲ | D84: ='Word List'!D91 -> han-ti | E84: ='Word List'!E91 -> one (feminine) | F84: ='Word List'!I91 -> ሓንቲ ጓል | G84: ='Word List'!J91 -> hanti gwal | H84: ='Word List'!K91 -> one girl
A85: ='Word List'!G168 -> Numbers & Amounts | B85: ='Word List'!A168 -> 167 | C85: ='Word List'!B168 -> ሰለስተ | D85: ='Word List'!D168 -> se-les-te | E85: ='Word List'!E168 -> three | F85: ='Word List'!I168 -> ሰለስተ ደቂ | G85: ='Word List'!J168 -> seleste deqi | H85: ='Word List'!K168 -> three children
A86: ='Word List'!G183 -> Numbers & Amounts | B86: ='Word List'!A183 -> 182 | C86: ='Word List'!B183 -> ቀዳማይ | D86: ='Word List'!D183 -> qe-da-may | E86: ='Word List'!E183 -> first | F86: ='Word List'!I183 -> ቀዳማይ ክፍሊ | G86: ='Word List'!J183 -> qedamay kifli | H86: ='Word List'!K183 -> first grade
A87: ='Word List'!G207 -> Numbers & Amounts | B87: ='Word List'!A207 -> 206 | C87: ='Word List'!B207 -> ካልኣይ | D87: ='Word List'!D207 -> kal-ay | E87: ='Word List'!E207 -> second | F87: ='Word List'!I207 -> ካልኣይ ክፍሊ | G87: ='Word List'!J207 -> kal'ay kifli | H87: ='Word List'!K207 -> second grade
A88: ='Word List'!G310 -> Numbers & Amounts | B88: ='Word List'!A310 -> 309 | C88: ='Word List'!B310 -> ኣርባዕተ | D88: ='Word List'!D310 -> ar-ba'-te | E88: ='Word List'!E310 -> four | F88: ='Word List'!I310 -> ኣርባዕተ እግሪ | G88: ='Word List'!J310 -> arba'te igri | H88: ='Word List'!K310 -> four legs
A89: ='Word List'!G399 -> Numbers & Amounts | B89: ='Word List'!A399 -> 398 | C89: ='Word List'!B399 -> ሓሙሽተ | D89: ='Word List'!D399 -> ha-mush-te | E89: ='Word List'!E399 -> five | F89: ='Word List'!I399 -> ሓሙሽተ ኣጻብዕ | G89: ='Word List'!J399 -> hamushte ats'abi' | H89: ='Word List'!K399 -> five fingers
A90: ='Word List'!G560 -> Numbers & Amounts | B90: ='Word List'!A560 -> 559 | C90: ='Word List'!B560 -> ሳልሳይ | D90: ='Word List'!D560 -> sal-say | E90: ='Word List'!E560 -> third | F90: ='Word List'!I560 -> ሳልሳይ ክፍሊ | G90: ='Word List'!J560 -> salsay kifli | H90: ='Word List'!K560 -> third grade
A91: ='Word List'!G690 -> Numbers & Amounts | B91: ='Word List'!A690 -> 689 | C91: ='Word List'!B690 -> ዓሰርተ | D91: ='Word List'!D690 -> a-ser-te | E91: ='Word List'!E690 -> ten | F91: ='Word List'!I690 -> ዓሰርተ ኣጻብዕ | G91: ='Word List'!J690 -> aserte ats'abi' | H91: ='Word List'!K690 -> ten fingers
A92: ='Word List'!G800 -> Numbers & Amounts | B92: ='Word List'!A800 -> 799 | C92: ='Word List'!B800 -> ሽዱሽተ | D92: ='Word List'!D800 -> shi-dush-te | E92: ='Word List'!E800 -> six | F92: ='Word List'!I800 -> ሽዱሽተ ዞባታት | G92: ='Word List'!J800 -> shidushte zobatat | H92: ='Word List'!K800 -> six regions
A93: ='Word List'!G935 -> Numbers & Amounts | B93: ='Word List'!A935 -> 934 | C93: ='Word List'!B935 -> ሓንሳብ | D93: ='Word List'!D935 -> han-sab | E93: ='Word List'!E935 -> once; one time | F93: ='Word List'!I935 -> ሓንሳብ ጥራይ | G93: ='Word List'!J935 -> hansab t'iray | H93: ='Word List'!K935 -> only once
A94: ='Word List'!G937 -> Numbers & Amounts | B94: ='Word List'!A937 -> 936 | C94: ='Word List'!B937 -> ሸውዓተ | D94: ='Word List'!D937 -> shew-a-te | E94: ='Word List'!E937 -> seven | F94: ='Word List'!I937 -> ሸውዓተ መዓልታት | G94: ='Word List'!J937 -> shew'ate me'altat | H94: ='Word List'!K937 -> seven days
A95: ='Word List'!G22 -> Time & Calendar | B95: ='Word List'!A22 -> 21 | C95: ='Word List'!B22 -> ግዜ | D95: ='Word List'!D22 -> gi-ze | E95: ='Word List'!E22 -> time | F95: ='Word List'!I22 -> ግዜ ድቃስ እዩ። | G95: ='Word List'!J22 -> gize diqas iyu. | H95: ='Word List'!K22 -> It's bedtime. (lit. "time of sleep")
A96: ='Word List'!G26 -> Time & Calendar | B96: ='Word List'!A26 -> 25 | C96: ='Word List'!B26 -> ዓመት | D96: ='Word List'!D26 -> a-met | E96: ='Word List'!E26 -> year | F96: ='Word List'!I26 -> ዕድመኡ ሸውዓተ ዓመት እዩ። | G96: ='Word List'!J26 -> idme'u shew'ate amet iyu. | H96: ='Word List'!K26 -> He is seven years old. (lit. "his age is seven years")
A97: ='Word List'!G38 -> Time & Calendar | B97: ='Word List'!A38 -> 37 | C97: ='Word List'!B38 -> ድሕሪ | D97: ='Word List'!D38 -> dih-ri | E97: ='Word List'!E38 -> after; behind | F97: ='Word List'!I38 -> ድሕሪ ትምህርቲ | G97: ='Word List'!J38 -> dihri timhirti | H97: ='Word List'!K38 -> after school
A98: ='Word List'!G61 -> Time & Calendar | B98: ='Word List'!A61 -> 60 | C98: ='Word List'!B61 -> ቅድሚ | D98: ='Word List'!D61 -> qid-mi | E98: ='Word List'!E61 -> before; in front of | F98: ='Word List'!I61 -> ቅድሚ ድቃስ | G98: ='Word List'!J61 -> qidmi diqas | H98: ='Word List'!K61 -> before sleeping
A99: ='Word List'!G72 -> Time & Calendar | B99: ='Word List'!A72 -> 71 | C99: ='Word List'!B72 -> ሕጂ | D99: ='Word List'!D72 -> hi-ji | E99: ='Word List'!E72 -> now | F99: ='Word List'!I72 -> ሕጂ ንዓ! | G99: ='Word List'!J72 -> hiji n'a! | H99: ='Word List'!K72 -> Come now! (to a boy)
A100: ='Word List'!G85 -> Time & Calendar | B100: ='Word List'!A85 -> 84 | C100: ='Word List'!B85 -> ሎሚ | D100: ='Word List'!D85 -> lo-mi | E100: ='Word List'!E85 -> today | F100: ='Word List'!I85 -> ሎሚ ሰንበት እዩ። | G100: ='Word List'!J85 -> lomi senbet iyu. | H100: ='Word List'!K85 -> Today is Sunday.
A101: ='Word List'!G93 -> Time & Calendar | B101: ='Word List'!A93 -> 92 | C101: ='Word List'!B93 -> መዓልቲ | D101: ='Word List'!D93 -> me-al-ti | E101: ='Word List'!E93 -> day | F101: ='Word List'!I93 -> ሰናይ መዓልቲ! | G101: ='Word List'!J93 -> senay me'alti! | H101: ='Word List'!K93 -> Have a good day!
...

Sheet Pronunciation Guide
A1: How to read the romanized pronunciations
A2: Tigrinya is written in the Ge'ez script (ፊደል). Each letter is a consonant + vowel. These spellings help English readers say the words.
A4: You see | B4: Say it like | C4: Ge'ez letters | D4: Example | E4: Example meaning
A5: VOWELS
A6: a | B6: 'a' in father | C6: ኣ ባ ማ | D6: ማይ — may | E6: water
A7: e | B7: 'e' in bed | C7: ሰ ቤ ከ | D7: ሰላም — se-lam | E7: hello; peace
A8: i | B8: 'i' in sit (often short and light) | C8: ኢ ብ ሚ | D8: ሕጂ — hi-ji | E8: now
A9: o | B9: 'o' in go | C9: ኦ ሎ ቦ | D9: ሎሚ — lo-mi | E9: today
A10: u | B10: 'oo' in food | C10: ኡ ሱ ቡ | D10: ንሱ — ni-su | E10: he
A11: SOUNDS ENGLISH DOESN'T HAVE
A12: t' | B12: 't' with a pop: hold your breath, then let the t burst out | C12: ጠ ጥ ጣ | D12: ጥራይ — t'i-ray | E12: only
A13: ts' | B13: 'ts' (as in cats) with a pop | C13: ጸ ጽ ጻ | D13: ጽቡቕ — ts'i-buq | E13: good
A14: ch' | B14: 'ch' with a pop | C14: ጨ ጭ ጫ | D14: ጫማ — ch'am-ma | E14: shoes
A15: p' | B15: 'p' with a pop | C15: ጰ ጵ | D15: ኢትዮጵያ — it-yo-p'i-ya | E15: Ethiopia
A16: q | B16: a deep 'k' made at the very back of the throat | C16: ቀ ቐ ቕ ቑ | D16: ቀይሕ — qe-yih | E16: red
A17: kh | B17: a soft, breathy throat sound, like the end of 'Bach' | C17: ኸ ኽ ኻ | D17: ኣምላኽ — am-lakh | E17: God
A18: h | B18: 'h' — ሐ/ሓ is a stronger, raspier h than ሀ/ሃ | C18: ሀ ሃ ሐ ሓ | D18: ሓደ — ha-de | E18: one
A19: ' (in the middle) | B19: a tiny catch in the throat, like the break in 'uh-oh' | C19: እ ዕ ዓ | D19: ማእከል — ma'-kel | E19: center
A20: FAMILIAR SOUNDS
A21: ch | B21: 'ch' in church | C21: ቸ ቹ | D21: ቸልሲ — chel-si | E21: Chelsea
A22: sh | B22: 'sh' in ship | C22: ሸ ሽ | D22: ሽሕ — shih | E22: thousand
A23: j | B23: 'j' in jam | C23: ጀ ጅ | D23: ጀመረ — je-me-re | E23: he started
A24: ny | B24: 'ny' in canyon | C24: ኘ ኛ | D24: ትግርኛ — tig-ri-nya | E24: Tigrinya
A25: gw / kw / qw | B25: round your lips for a little 'w' | C25: ጓ ኳ ቋ | D25: ቋንቋ — qwan-qwa | E25: language
A26: READING TIPS
A27: Hyphens | B27: Separate syllables. Say each part clearly and evenly. | D27: ትምህርቲ — tim-hir-ti | E27: education
A28: Double letters | B28: Hold the sound a little longer. | D28: ኩሉ — kul-lu | E28: all
A29: k → kh | B29: After a vowel, k often softens to kh, and the spelling can change too. | C29: ከ → ኸ | D29: ከም → ኸም | E29: like, as
A30: Apostrophes in examples | B30: In example sentences, a word like izi'yu shows a contraction, the same as in the Tigrinya (እዚ'ዩ). | D30: እዚ'ዩ — izi'yu | E30: this is it

Sheet Word List
A1: Rank | B1: Tigrinya Word | C1: Frequency | D1: Pronunciation | E1: English Meaning | F1: Word Type | G1: Topic | H1: Level | I1: Example (Tigrinya) | J1: Example (Romanized) | K1: Example (English) | L1: Learning Note | M1: Needs Review
A2: 1 | B2: ኣብ | C2: 2047826 | D2: ab | E2: at, in, on | F2: Preposition | G2: Grammar Essentials | H2: 1 Starter | I2: ኣብ ገዛ ኣለኹ። | J2: ab geza allekhu. | K2: I am at home. | L2: The #1 most common word in Tigrinya. It tells WHERE something is. Often joins the next word: ኣብቲ (in the), ኣብዚ (here).
A3: 2 | B3: ናይ | C3: 675275 | D3: nay | E3: of; belonging to ('s) | F3: Preposition | G3: Grammar Essentials | H3: 1 Starter | I3: ናይ ኣደይ መኪና | J3: nay adey mekina | K3: my mother's car | L3: Works like English "'s" or "of". ናይ መን? = whose?
A4: 3 | B4: እዩ | C4: 583384 | D4: i-yu | E4: is (he/it is) | F4: Linking word (is/am/are) | G4: Grammar Essentials | H4: 1 Starter | I4: እዚ ማይ እዩ። | J4: izi may iyu. | K4: This is water. | L4: A linking word that goes at the END of the sentence. It changes with the subject: እየ (I am), ኢኻ (you are), እያ (she is), እዮም (they are).
A5: 4 | B5: ካብ | C5: 562897 | D5: kab | E5: from | F5: Preposition | G5: Grammar Essentials | H5: 1 Starter | I5: ካብ ኣስመራ እየ። | J5: kab asmera iye. | K5: I am from Asmara. | L5: After a vowel it can be written ኻብ (khab). ካብ ... ክሳብ = from ... until.
A6: 5 | B6: ከም | C6: 494067 | D6: kem | E6: like, as | F6: Preposition | G6: Grammar Essentials | H6: 1 Starter | I6: ከም ኣቦኻ ኢኻ። | J6: kem abokha ikha. | K6: You are like your father. | L6: After a vowel it often softens to ኸም (khem). ከምዚ = like this.
A7: 6 | B7: እቲ | C7: 493726 | D7: i-ti | E7: the; that (masculine) | F7: Pointing word (the/this/that) | G7: Grammar Essentials | H7: 1 Starter | I7: እቲ ቈልዓ ይጻወት ኣሎ። | J7: iti qol'a yits'awet allo. | K7: The child is playing. | L7: Used with masculine words. Feminine: እታ. Plural: እቶም / እተን.
A8: 7 | B8: ድማ | C8: 450747 | D8: dim-ma | E8: and; also | F8: Connector (conjunction) | G8: Grammar Essentials | H8: 1 Starter | I8: ኣነ ድማ ክመጽእ እየ። | J8: ane dimma kimets'i iye. | K8: And I will come too. | L8: Comes AFTER the word it links (ኣነ ድማ = "and I"). Means about the same as ከኣ.
A9: 8 | B9: ምስ | C9: 449626 | D9: mis | E9: with | F9: Preposition | G9: Grammar Essentials | H9: 1 Starter | I9: ምስ ኣደይ ከይደ። | J9: mis adey keyde. | K9: I went with my mother. | L9: Before a verb it can mean "when": ምስ መጸ = when he came.
A10: 9 | B10: ናብ | C10: 329635 | D10: nab | E10: to, toward | F10: Preposition | G10: Grammar Essentials | H10: 1 Starter | I10: ናብ ቤት ትምህርቲ ንኸይድ ኣለና። | J10: nab bet timhirti nikheyd allena. | K10: We are going to school. | L10: Shows direction (where you are going). ናብዚ = to here.
A11: 10 | B11: እዚ | C11: 297664 | D11: i-zi | E11: this (masculine) | F11: Pointing word (the/this/that) | G11: Grammar Essentials | H11: 1 Starter | I11: እዚ እንታይ እዩ? | J11: izi intay iyu? | K11: What is this? | L11: Feminine: እዛ. Plural: እዞም / እዘን. One of the first words to learn!
A12: 11 | B12: ዩ | C12: 267828 | D12: yu | E12: is (short form of እዩ) | F12: Short / split form | G12: Grammar Essentials | H12: 2 Core | I12: እዚ'ዩ። | J12: izi'yu. | K12: This is it. | L12: Contracted form of እዩ, written after an apostrophe when the word before ends in a vowel. It shows up as its own "word" because of how the text was split.
A13: 12 | B13: ነቲ | C13: 216027 | D13: ne-ti | E13: the (as the object); to the (masculine) | F13: Pointing word (the/this/that) | G13: Grammar Essentials | H13: 2 Core | I13: ነቲ መጽሓፍ ሃበኒ። | J13: neti mets'haf habeni. | K13: Give me the book. | L13: ን + እቲ. Used when "the ___" receives the action. Feminine: ነታ.
... A65: 64 | B65: ዓለም | C65: 72009 | D65: a-lem | E65: world | F65: Noun | G65: Places & Geography | H65: 2 Core | I65: ኣብ ምሉእ ዓለም | J65: ab milu' alem | K65: in the whole world | L65: Also a girl's name (ዓለም).
A66: 65 | B66: ኮይኑ | C66: 71805 | D66: koy-nu | E66: being; having become | F66: Verb form | G66: Grammar Essentials | H66: 3 Advanced | I66: ሓሚሙ ኮይኑ። | J66: hamimu koynu. | K66: It turns out he is sick. | L66: From ኮነ (became; was). Variant spellings: ኰይኑ, ዀይኑ. | M66: Check
A67: 66 | B67: ዘለዎ | C67: 71773 | D67: zel-le-wo | E67: that has; which (he/it) has | F67: Verb form | G67: Grammar Essentials | H67: 3 Advanced | I67: ቀይሕ መኪና ዘለዎ ሰብ | J67: qeyih mekina zellewo seb | K67: the man who has a red car | L67: From ኣለዎ (he has).
A68: 67 | B68: ስራሕ | C68: 70712 | D68: si-rah | E68: work; job | F68: Noun | G68: Work & Money | H68: 1 Starter | I68: ኣቦይ ናብ ስራሕ ከይዱ። | J68: aboy nab sirah keydu. | K68: My dad went to work. | L68: Plural: ስራሓት. ዕዮ also means work.
A69: 68 | B69: ኢሉ | C69: 69907 | D69: i-lu | E69: saying; having said (he) | F69: Verb form | G69: Grammar Essentials | H69: 2 Core | I69: "ሰላም" ኢሉ። | J69: "selam" ilu. | K69: He said "hello". | L69: From በለ (to say). She said: ኢላ. They said: ኢሎም.
A70: 69 | B70: ክልተ | C70: 69688 | D70: kil-te | E70: two | F70: Number | G70: Numbers & Amounts | H70: 1 Starter | I70: ክልተ ኣዒንቲ | J70: kilte a'inti | K70: two eyes | L70: Number 2. ካልኣይ = second.
A71: 70 | B71: ዝብል | C71: 69273 | D71: zi-bil | E71: that says; called | F71: Verb form | G71: Grammar Essentials | H71: 3 Advanced | I71: ሰላም ዝብል ቃል | J71: selam zibil qal | K71: the word "selam" (lit. "the word that says selam") | L71: From ይብል (he says). Used for quotes and titles.
A72: 71 | B72: ሕጂ | C72: 69041 | D72: hi-ji | E72: now | F72: Adverb | G72: Time & Calendar | H72: 1 Starter | I72: ሕጂ ንዓ! | J72: hiji n'a! | K72: Come now! (to a boy) | L72: ክሳብ ሕጂ = until now.
A73: 72 | B73: ነገር | C73: 68381 | D73: ne-ger | E73: thing; matter | F73: Noun | G73: Home & Everyday Life | H73: 1 Starter | I73: እዚ ነገር እንታይ እዩ? | J73: izi neger intay iyu? | K73: What is this thing? | L73: Plural: ነገራት.
A74: 73 | B74: እንተሎ | C74: 67075 | D74: in-tel-lo | E74: if there is | F74: Verb form | G74: Grammar Essentials | H74: 3 Advanced | I74: ሕቶ እንተሎ ሕተቱ። | J74: hito intello hitetu. | K74: If there is a question, ask. | L74: እንተ (if) + ኣሎ (there is). Very common here from court notices: ዝቃወም እንተሎ = "if anyone objects".
A75: 74 | B75: ብዙሕ | C75: 66437 | D75: bi-zuh | E75: much; many; a lot | F75: Adjective | G75: Describing Words | H75: 1 Starter | I75: ብዙሕ የቐንየለይ። | J75: bizuh yeqenyeley. | K75: Thank you very much. | L75: Plural form: ብዙሓት. A must-know phrase!
A76: 75 | B76: ኩሉ | C76: 65760 | D76: kul-lu | E76: all; everything | F76: Adjective | G76: Describing Words | H76: 1 Starter | I76: ኩሉ ጽቡቕ እዩ። | J76: kullu ts'ibuq iyu. | K76: Everything is good. | L76: ኩሎም = all of them (people). Variant spellings: ኵሉ, ዅሉ.
A77: 76 | B77: ከተማ | C77: 65392 | D77: ke-te-ma | E77: city, town | F77: Noun | G77: Places & Geography | H77: 1 Starter | I77: ኣስመራ ርእሰ ከተማ ኤርትራ እያ። | J77: asmera ri'se ketema ertra iya. | K77: Asmara is the capital city of Eritrea. | L77: Plural: ከተማታት.
A78: 77 | B78: ገለ | C78: 65240 | D78: ge-le | E78: some; something | F78: Adjective | G78: Describing Words | H78: 2 Core | I78: ገለ ማይ ሃበኒ። | J78: gele may habeni. | K78: Give me some water. (to a man/boy) | L78: ገለ ነገር = something. ገሊኦም = some of them.
... A174: 173 | B174: ከመይ | C174: 33742 | D174: ke-mey | E174: how? | F174: Question word | G174: Questions | H174: 1 Starter | I174: ከመይ ኣለኻ? | J174: kemey allekha? | K174: How are you? (to a boy/man) | L174: The #1 greeting! To a girl: ከመይ ኣለኺ? To a group: ከመይ ኣለኹም? Answer: ደሓን እየ (I'm fine).
A175: 174 | B175: ኮማዊ | C175: 33684 | D175: ko-ma-wi | E175: (meaning uncertain) | F175: Adjective | G175: News & Government | H175: 4 Specialized | I175: — | J175: — | K175: — | L175: Appears very often in the source data (probably in formal/official notices) but is rare in everyday Tigrinya. Please confirm the meaning with a fluent speaker before teaching it. | M175: Check
A176: 175 | B176: ብኸመይ | C176: 33659 | D176: bi-khe-mey | E176: how? in what way? | F176: Question word | G176: Questions | H176: 2 Core | I176: ብትግርኛ ብኸመይ ይበሃል? | J176: bitigrinya bikhemey yibehal? | K176: How do you say it in Tigrinya? | L176: Super useful for learners! ብ + ከመይ.
A177: 176 | B177: ሕማም | C177: 33585 | D177: hi-mam | E177: illness; disease; pain | F177: Noun | G177: Body & Health | H177: 2 Core | I177: ሕማም ርእሲ | J177: himam ri'si | K177: headache | L177: ሓሚመ = I'm sick. Plural: ሕማማት.
A178: 177 | B178: እዛ | C178: 33536 | D178: i-za | E178: this (feminine) | F178: Pointing word (the/this/that) | G178: Grammar Essentials | H178: 1 Starter | I178: እዛ ጓል ሓብተይ እያ። | J178: iza gwal habtey iya. | K178: This girl is my sister. | L178: Feminine of እዚ.
A179: 178 | B179: መንጎ | C179: 33461 | D179: men-go | E179: between; among | F179: Preposition | G179: Grammar Essentials | H179: 2 Core | I179: ኣብ መንጎ ክልተ ገዛውቲ | J179: ab mengo kilte gezawti | K179: between two houses | L179: ኣብ መንጎ = between.
A180: 179 | B180: ጸወታ | C180: 33205 | D180: ts'e-we-ta | E180: game; play | F180: Noun | G180: Sports & Games | H180: 1 Starter | I180: ጸወታ ኩዕሶ | J180: ts'eweta ku'so | K180: a ball game | L180: Plural: ጸወታታት. ንጻወት! = Let's play!
A181: 180 | B181: ሰዓት | C181: 33199 | D181: se-at | E181: hour; o'clock; clock, watch | F181: Noun | G181: Time & Calendar | H181: 1 Starter | I181: ሰዓት ክንደይ እዩ? | J181: se'at kindey iyu? | K181: What time is it? | L181: Must-know question! Plural: ሰዓታት.
A182: 181 | B182: ዝበለ | C182: 33160 | D182: zi-be-le | E182: who said; that said | F182: Verb form | G182: Grammar Essentials | H182: 3 Advanced | I182: ሰላም ዝበለ ሰብ | J182: selam zibele seb | K182: the person who said hello | L182: From በለ (said). Plural: ዝበሉ.
A183: 182 | B183: ቀዳማይ | C183: 33142 | D183: qe-da-may | E183: first | F183: Adjective | G183: Numbers & Amounts | H183: 1 Starter | I183: ቀዳማይ ክፍሊ | J183: qedamay kifli | K183: first grade | L183: Feminine: ቀዳመይቲ. Second: ካልኣይ. Third: ሳልሳይ.
A184: 183 | B184: የሱስ | C184: 33129 | D184: ye-sus | E184: Jesus | F184: Other name | G184: Faith & Religion | H184: 2 Core | I184: የሱስ ክርስቶስ | J184: yesus kristos | K184: Jesus Christ | L184: Heard often in church and Christian homes.
A185: 184 | B185: ሕጊ | C185: 32717 | D185: hi-gi | E185: law; rule | F185: Noun | G185: Law & Courts | H185: 3 Advanced | I185: ሕጊ ቤት ትምህርቲ | J185: higi bet timhirti | K185: school rules | L185: Plural: ሕግታት. ሕጋዊ = legal.
A186: 185 | B186: ዋላ | C186: 32500 | D186: wal-la | E186: even; even if | F186: Particle | G186: Grammar Essentials | H186: 2 Core | I186: ዋላ ሓደ | J186: walla hade | K186: not even one; none | L186: ዋላ'ኳ = even though.
A187: 186 | B187: ክብል | C187: 32439 | D187: ki-bil | E187: saying; to say | F187: Verb form | G187: Grammar Essentials | H187: 3 Advanced | I187: ... ክብል ሓቲቱ። | J187: ... kibil hatitu. | K187: he asked, saying ... | L187: Infinitive of በለ. Introduces what someone said.
... A311: 310 | B311: ስርዓት | C311: 20870 | D311: sir-at | E311: system; order; ceremony | F311: Noun | G311: News & Government | H311: 3 Advanced | I311: ስርዓት መርዓ | J311: sir'at mer'a | K311: wedding ceremony | L311: Also "good order/discipline".
A312: 311 | B312: ቤተይ | C312: 20795 | D312: be-tey | E312: my household; my home | F312: Noun | G312: Home & Everyday Life | H312: 4 Specialized | I312: ሰብ ቤተይ | J312: seb betey | K312: my spouse; my household | L312: Literally "my house" (poetic/formal). Its high count may come from set phrases in notices; check usage with a fluent speaker. | M312: Check
A313: 312 | B313: ክንደይ | C313: 20781 | D313: kin-dey | E313: how much? how many? | F313: Question word | G313: Questions | H313: 1 Starter | I313: ክንደይ እዩ? | J313: kindey iyu? | K313: How much is it? | L313: Must-know! ዕድመኻ ክንደይ እዩ? = How old are you?
A314: 313 | B314: ተራ | C314: 20669 | D314: te-ra | E314: turn; role; ordinary | F314: Noun | G314: Home & Everyday Life | H314: 2 Core | I314: ተራኻ እዩ። | J314: terakha iyu. | K314: It's your turn. (to a boy) | L314: Also means "ordinary" and "role".
A315: 314 | B315: መግለጺ | C315: 20640 | D315: meg-le-ts'i | E315: statement; description | F315: Noun | G315: News & Government | H315: 3 Advanced | I315: መግለጺ ሚኒስትሪ | J315: meglets'i ministri | K315: a ministry statement | L315: From ገለጸ (to explain).
A316: 315 | B316: ኣገዳሲ | C316: 20601 | D316: a-ge-da-si | E316: important | F316: Adjective | G316: Describing Words | H316: 2 Core | I316: ኣዝዩ ኣገዳሲ እዩ። | J316: azyu agedasi iyu. | K316: It's very important. | L316: Feminine: ኣገዳሲት.
A317: 316 | B317: ጋዜጣ | C317: 20590 | D317: ga-ze-t'a | E317: newspaper | F317: Noun | G317: News & Government | H317: 3 Advanced | I317: ጋዜጣ ሓዳስ ኤርትራ | J317: gazet'a hadas ertra | K317: the Hadas Eritrea newspaper | L317: From Italian "gazzetta".
A318: 317 | B318: የለን | C318: 20569 | D318: ye-len | E318: there isn't; no; is not here | F318: Verb form | G318: Grammar Essentials | H318: 1 Starter | I318: ኣቦይ ኣብ ገዛ የለን። | J318: aboy ab geza yelen. | K318: My dad isn't home. | L318: Negative of ኣሎ. Common short answer: የለን = "there's none / no".
A319: 318 | B319: ብመሰረት | C319: 20492 | D319: bi-me-se-ret | E319: according to; based on | F319: Preposition | G319: Grammar Essentials | H319: 3 Advanced | I319: ብመሰረት ሕጊ | J319: bimeseret higi | K319: according to the law | L319: From መሰረት (foundation).
A320: 319 | B320: ሰላም | C320: 20481 | D320: se-lam | E320: hello; peace | F320: Noun | G320: Feelings & Values | H320: 1 Starter | I320: ሰላም! ከመይ ኣለኻ? | J320: selam! kemey allekha? | K320: Hello! How are you? (to a boy) | L320: The everyday greeting AND the word for peace.
A321: 320 | B321: ጽሕፈት | C321: 20270 | D321: ts'ih-fet | E321: writing; office (in ቤት ጽሕፈት) | F321: Noun | G321: School & Language | H321: 3 Advanced | I321: ቤት ጽሕፈት | J321: bet ts'ihfet | K321: office | L321: From ጸሓፈ (to write).
A322: 321 | B322: ተጻወትቲ | C322: 20259 | D322: te-ts'a-wet-ti | E322: players | F322: Noun | G322: Sports & Games | H322: 2 Core | I322: ዓሰርተ ሓደ ተጻወትቲ | J322: aserte hade tets'awetti | K322: eleven players | L322: Plural of ተጻዋታይ.
A323: 322 | B323: መጽናዕቲ | C323: 20245 | D323: mets'-na'-ti | E323: study; research | F323: Noun | G323: School & Language | H323: 3 Advanced | I323: መጽናዕቲ ይገልጽ | J323: mets'na'ti yigelts' | K323: research shows | L323: Formal word.
A324: 323 | B324: ደም | C324: 20207 | D324: dem | E324: blood | F324: Noun | G324: Body & Health | H324: 2 Core | I324: ቀይሕ ደም | J324: qeyih dem | K324: red blood | L324: Used in health and science.
... A492: 491 | B492: ታሕሳስ | C492: 13967 | D492: tah-sas | E492: December | F492: Noun | G492: Time & Calendar | H492: 2 Core | I492: ኣብ ታሕሳስ | J492: ab tahsas | K492: in December | L492: The 12th month.
A493: 492 | B493: መሰለይ | C493: 13963 | D493: me-se-ley | E493: my right | F493: Noun | G493: Law & Courts | H493: 4 Specialized | I493: መሰለይ ይሕለወለይ | J493: meseley yihleweley | K493: may my right be protected | L493: From መሰል (right), common in court notices. (It could also be read as "it seemed to me"; confirm context.) | M493: Check
A494: 493 | B494: ፍልጠት | C494: 13977 | D494: fil-t'et | E494: knowledge | F494: Noun | G494: School & Language | H494: 2 Core | I494: ፍልጠት ሓይሊ እዩ። | J494: filt'et hayli iyu. | K494: Knowledge is power. | L494: From ፈለጠ (to know).
A495: 494 | B495: ናይዚ | C495: 13916 | D495: nay-zi | E495: of this | F495: Preposition | G495: Grammar Essentials | H495: 2 Core | I495: ናይዚ ዓመት | J495: nayzi amet | K495: this year's | L495: ናይ + እዚ.
A496: 495 | B496: ምዃና | C496: 13911 | D496: mi-khwa-na | E496: that she is | F496: Verb form | G496: Grammar Essentials | H496: 3 Advanced | I496: ጐባዝ ምዃና | J496: gobaz mikhwana | K496: that she is smart | L496: Feminine of ምዃኑ.
A497: 496 | B497: ሜዳ | C497: 13903 | D497: me-da | E497: field; open ground | F497: Noun | G497: Sports & Games | H497: 2 Core | I497: ሜዳ ኩዕሶ | J497: meda ku'so | K497: soccer field | L497: In Eritrean history, ሜዳ also refers to "the field" of the liberation struggle.
A498: 497 | B498: ዳርጋ | C498: 13877 | D498: dar-ga | E498: almost; nearly | F498: Adverb | G498: Describing Words | H498: 2 Core | I498: ዳርጋ ወዲአ። | J498: darga wedi'e. | K498: I'm almost done. | L498: Similar: ቀሪቡ.
A499: 498 | B499: ተወሳኺ | C499: 13851 | D499: te-we-sa-khi | E499: additional; extra | F499: Adjective | G499: Describing Words | H499: 3 Advanced | I499: ተወሳኺ ሓበሬታ | J499: tewesakhi habereta | K499: additional information | L499: ብተወሳኺ = in addition.
A500: 499 | B500: ቤተ | C500: 13944 | D500: be-te | E500: house of (in compounds) | F500: Word part (compounds) | G500: Faith & Religion | H500: 3 Advanced | I500: ቤተ ክርስቲያን | J500: bete kristiyan | K500: church | L500: Used in compounds: ቤተ መጻሕፍቲ (library), ቤተሰብ (family).
A501: 500 | B501: ክርስቶስ | C501: 13763 | D501: kris-tos | E501: Christ | F501: Other name | G501: Faith & Religion | H501: 3 Advanced | I501: ልደት ክርስቶስ | J501: lidet kristos | K501: Christmas (the birth of Christ) | L501: Many Eritrean Christians celebrate Christmas (ልደት) on January 7.
A502: 501 | B502: ፍጹም | C502: 13757 | D502: fi-ts'um | E502: perfect; complete; absolutely | F502: Adjective | G502: Describing Words | H502: 2 Core | I502: ፍጹም ጽቡቕ | J502: fits'um ts'ibuq | K502: perfectly good | L502: Also a name (ፍጹም).
A503: 502 | B503: ሕቡራት | C503: 13691 | D503: hi-bu-rat | E503: united | F503: Adjective | G503: News & Government | H503: 3 Advanced | I503: ሕቡራት ሃገራት | J503: hiburat hagerat | K503: the United Nations | L503: ሕቡራት መንግስታት ኣመሪካ = the United States of America!
A504: 503 | B504: ጽባሕ | C504: 13670 | D504: ts'i-bah | E504: tomorrow | F504: Adverb | G504: Time & Calendar | H504: 1 Starter | I504: ጽባሕ ንራኸብ። | J504: ts'ibah nirakheb. | K504: See you tomorrow. (lit. "let's meet tomorrow") | L504: ትማሊ = yesterday. ሎሚ = today.
A505: 504 | B505: ሓዳር | C505: 13668 | D505: ha-dar | E505: marriage; household | F505: Noun | G505: People & Family | H505: 3 Advanced | I505: ጽቡቕ ሓዳር | J505: ts'ibuq hadar | K505: a happy marriage | L505: ሓዳር ገበረ = he got married.
... A762: 761 | B762: ጽልዋ | C762: 9632 | D762: ts'il-wa | E762: influence; impact | F762: Noun | G762: News & Government | H762: 3 Advanced | I762: ጽቡቕ ጽልዋ | J762: ts'ibuq ts'ilwa | K762: a good influence | L762: Formal word.
A763: 762 | B763: መጋባኣያ | C763: 9582 | D763: me-ga-ba-a-ya | E763: court hearing; session hall | F763: Noun | G763: Law & Courts | H763: 4 Specialized | I763: ኣብ መጋባኣያ ቤት ፍርዲ | J763: ab megaba'aya bet firdi | K763: at the court hearing | L763: From court notices; more often spelled መጋባእያ. | M763: Check
A764: 763 | B764: መላእ | C764: 9581 | D764: me-la' | E764: whole; entire | F764: Adjective | G764: Describing Words | H764: 3 Advanced | I764: መላእ ዓለም | J764: mela' alem | K764: the whole world | L764: Similar: ምሉእ.
A765: 764 | B765: ዀነ | C765: 9562 | D765: kho-ne | E765: became; was (variant of ኮነ) | F765: Verb form | G765: Grammar Essentials | H765: 3 Advanced | I765: ከምኡ ዀነ። | J765: kem'u khone. | K765: It happened like that. | L765: Older spelling of ኮነ, written with ዀ after a vowel.
A766: 765 | B766: ኣእምሮ | C766: 9591 | D766: a-'im-ro | E766: mind; brain | F766: Noun | G766: Body & Health | H766: 2 Core | I766: ጥዕና ኣእምሮ | J766: t'i'na a'imro | K766: mental health | L766: Plural: ኣእምሮታት.
A767: 766 | B767: እንስሳታት | C767: 9561 | D767: in-si-sa-tat | E767: animals | F767: Noun | G767: Nature & Animals | H767: 2 Core | I767: ናይ ገዛ እንስሳታት | J767: nay geza insisatat | K767: pets; home animals | L767: Plural of እንስሳ.
A768: 767 | B768: መራሒ | C768: 9560 | D768: me-ra-hi | E768: leader; guide | F768: Noun | G768: News & Government | H768: 3 Advanced | I768: መራሒ ጋንታ | J768: merahi ganta | K768: team captain | L768: Plural: መራሕቲ.
A769: 768 | B769: ክርስትያን | C769: 9555 | D769: kris-ti-yan | E769: Christian | F769: Noun | G769: Faith & Religion | H769: 3 Advanced | I769: ክርስትያን ኢና። | J769: kristiyan ina. | K769: We are Christians. | L769: Plural: ክርስትያናት.
A770: 769 | B770: ክትብል | C770: 9548 | D770: kit-bil | E770: saying (she/you) | F770: Verb form | G770: Grammar Essentials | H770: 3 Advanced | I770: ... ክትብል ሓቲታ። | J770: ... kitbil hatita. | K770: she asked, saying ... | L770: From በለ.
A771: 770 | B771: ምልክት | C771: 9527 | D771: mil-kit | E771: sign; signal; mark | F771: Noun | G771: School & Language | H771: 2 Core | I771: ምልክት መገዲ | J771: milkit megedi | K771: road sign | L771: ምልክታ = notice.
A772: 771 | B772: ነተን | C772: 9507 | D772: ne-ten | E772: the (as object; feminine plural) | F772: Pointing word (the/this/that) | G772: Grammar Essentials | H772: 3 Advanced | I772: ነተን ኣዋልድ ሓግዘን። | J772: neten awalid hagizen. | K772: Help the girls. (to a boy) | L772: ን + እተን.
A773: 772 | B773: ናጻ | C773: 9517 | D773: na-ts'a | E773: free | F773: Adjective | G773: News & Government | H773: 2 Core | I773: ናጻ ሃገር | J773: nats'a hager | K773: a free country | L773: Also "free of charge": ብናጻ.
A774: 773 | B774: ስለዝሞተት | C774: 9505 | D774: si-lez-mo-tet | E774: because she died | F774: Verb form | G774: Law & Courts | H774: 4 Specialized | I774: ... ስለዝሞተት | J774: ... silezmotet | K774: since she passed away | L774: Set phrase from inheritance notices. Sensitive for children.
A775: 774 | B775: ንእሽቶ | C775: 9497 | D775: ni-'ish-to | E775: small; little; young | F775: Adjective | G775: Describing Words | H775: 1 Starter | I775: ንእሽቶ ሓብተይ | J775: ni'ishto habtey | K775: my little sister | L775: Opposite: ዓቢ (big).
... A817: 816 | B817: ብምጥቃስ | C817: 8971 | D817: bim-t'i-qas | E817: citing; quoting | F817: Verb form | G817: News & Government | H817: 4 Specialized | I817: ጋዜጣ ብምጥቃስ | J817: gazet'a bimt'iqas | K817: citing a newspaper | L817: News word.
A818: 817 | B818: ነፍ | C818: 8961 | D818: nef | E818: (part of ነፍ ወከፍ, "each") | F818: Short / split form | G818: Numbers & Amounts | H818: 4 Specialized | I818: ነፍ ወከፍ | J818: nef wekef | K818: each one | L818: Probably a split piece of ነፍ-ወከፍ / ነፍሲ ወከፍ (each, every). Confirm with a fluent speaker. | M818: Check
A819: 818 | B819: መዝሙር | C819: 8960 | D819: mez-mur | E819: hymn; psalm; song | F819: Noun | G819: Faith & Religion | H819: 2 Core | I819: መዝሙር ዳዊት | J819: mezmur dawit | K819: the Psalms of David | L819: Church songs. Plural: መዛሙር.
A820: 819 | B820: ክካየድ | C820: 8955 | D820: kik-ka-yed | E820: to be held; to take place | F820: Verb form | G820: News & Government | H820: 3 Advanced | I820: ጽባሕ ክካየድ እዩ። | J820: ts'ibah kikkayed iyu. | K820: It will be held tomorrow. | L820: Formal word.
A821: 820 | B821: ሃብቲ | C821: 8967 | D821: hab-ti | E821: wealth; riches | F821: Noun | G821: Work & Money | H821: 3 Advanced | I821: ሃብቲ ባሕሪ | J821: habti bahri | K821: marine resources | L821: Also a girl's name.
A822: 821 | B822: ፈረንሳ | C822: 8960 | D822: fe-ren-sa | E822: France | F822: Place name | G822: Places & Geography | H822: 3 Advanced | I822: ኣብ ፈረንሳ | J822: ab ferensa | K822: in France | L822: Place name.
A823: 822 | B823: ማን | C823: 8960 | D823: man | E823: "Man" (short for Manchester) | F823: Other name | G823: Sports & Games | H823: 4 Specialized | I823: ማን ዩናይትድ | J823: man yunaytid | K823: Man United | L823: From sports news.
A824: 823 | B824: ሰብኣዊ | C824: 8931 | D824: seb-a-wi | E824: human; humanitarian | F824: Adjective | G824: News & Government | H824: 3 Advanced | I824: ሰብኣዊ መሰል | J824: seb'awi mesel | K824: human rights | L824: From ሰብ (person).
A825: 824 | B825: መብዛሕትኡ | C825: 8907 | D825: meb-zah-ti-u | E825: most of it; mostly | F825: Adverb | G825: Numbers & Amounts | H825: 3 Advanced | I825: መብዛሕትኡ ግዜ | J825: mebzahti'u gize | K825: most of the time | L825: From ብዙሕ.
A826: 825 | B826: ወገናት | C826: 8897 | D826: we-ge-nat | E826: relatives; fellow people | F826: Noun | G826: People & Family | H826: 3 Advanced | I826: ወገናትና | J826: wegenatna | K826: our people; our relatives | L826: Plural of ወገን.
A827: 826 | B827: ሻምፕዮን | C827: 8895 | D827: shamp-yon | E827: champion | F827: Noun | G827: Sports & Games | H827: 3 Advanced | I827: ሻምፕዮን ዓለም | J827: shampyon alem | K827: world champion | L827: Loanword.
A828: 827 | B828: ከምዘለዎ | C828: 8882 | D828: kem-zel-le-wo | E828: that he has | F828: Verb form | G828: Grammar Essentials | H828: 3 Advanced | I828: ሓይሊ ከምዘለዎ | J828: hayli kemzellewo | K828: that he has strength | L828: ከም + ዘለዎ.
A829: 828 | B829: ዘበለ | C829: 8870 | D829: ze-be-le | E829: every; whatever (in ዝኾነ ዘበለ) | F829: Adjective | G829: Grammar Essentials | H829: 3 Advanced | I829: ዝኾነ ዘበለ | J829: zikhone zebele | K829: anything at all | L829: Adds an "any/every" meaning.
A830: 829 | B830: ብምኽንያት | C830: 8870 | D830: bim-khin-yat | E830: on the occasion of; because of | F830: Preposition | G830: Grammar Essentials | H830: 3 Advanced | I830: ብምኽንያት በዓል ናጽነት | J830: bimkhinyat be'al nats'inet | K830: on the occasion of Independence Day | L830: ብ + ምኽንያት.
... A887: 886 | B887: ህንጻ | C887: 8302 | D887: hin-ts'a | E887: building | F887: Noun | G887: Places & Geography | H887: 2 Core | I887: ነዊሕ ህንጻ | J887: newih hints'a | K887: a tall building | L887: Plural: ህንጻታት.
A888: 887 | B888: ሎ | C888: 8286 | D888: lo | E888: is; there is (short form of ኣሎ) | F888: Short / split form | G888: Grammar Essentials | H888: 3 Advanced | I888: እንታይ'ሎ? | J888: intay'lo? | K888: What's up? (lit. "what is there?") | L888: Contracted form of ኣሎ, attached with an apostrophe. | M888: Check
A889: 888 | B889: ሙሴ | C889: 8274 | D889: mu-se | E889: Moses | F889: Person's name | G889: Names | H889: 4 Specialized | I889: ነብዪ ሙሴ | J889: nebiyi muse | K889: the prophet Moses | L889: Biblical name.
...

Sheet Summary
A1: Summary — words by topic and level
A2: All counts are formulas over the Word List and update if you change a Topic or Level there.
A4: Topic | B4: 1 Starter | C4: 2 Core | D4: 3 Advanced | E4: 4 Specialized | F4: Total
A5: Actions | B5: =COUNTIFS('Word List'!$G$2:$G$1001,$A5,'Word List'!$H$2:$H$1001,B$4) -> 3 | C5: =COUNTIFS('Word List'!$G$2:$G$1001,$A5,'Word List'!$H$2:$H$1001,C$4) -> 24 | D5: =COUNTIFS('Word List'!$G$2:$G$1001,$A5,'Word List'!$H$2:$H$1001,D$4) -> 4 | E5: =COUNTIFS('Word List'!$G$2:$G$1001,$A5,'Word List'!$H$2:$H$1001,E$4) -> 0 | F5: =SUM(B5:E5) -> 31
A6: Body & Health | B6: =COUNTIFS('Word List'!$G$2:$G$1001,$A6,'Word List'!$H$2:$H$1001,B$4) -> 6 | C6: =COUNTIFS('Word List'!$G$2:$G$1001,$A6,'Word List'!$H$2:$H$1001,C$4) -> 11 | D6: =COUNTIFS('Word List'!$G$2:$G$1001,$A6,'Word List'!$H$2:$H$1001,D$4) -> 9 | E6: =COUNTIFS('Word List'!$G$2:$G$1001,$A6,'Word List'!$H$2:$H$1001,E$4) -> 0 | F6: =SUM(B6:E6) -> 26
A7: Culture & Celebrations | B7: =COUNTIFS('Word List'!$G$2:$G$1001,$A7,'Word List'!$H$2:$H$1001,B$4) -> 1 | C7: =COUNTIFS('Word List'!$G$2:$G$1001,$A7,'Word List'!$H$2:$H$1001,C$4) -> 8 | D7: =COUNTIFS('Word List'!$G$2:$G$1001,$A7,'Word List'!$H$2:$H$1001,D$4) -> 1 | E7: =COUNTIFS('Word List'!$G$2:$G$1001,$A7,'Word List'!$H$2:$H$1001,E$4) -> 0 | F7: =SUM(B7:E7) -> 10
A8: Describing Words | B8: =COUNTIFS('Word List'!$G$2:$G$1001,$A8,'Word List'!$H$2:$H$1001,B$4) -> 15 | C8: =COUNTIFS('Word List'!$G$2:$G$1001,$A8,'Word List'!$H$2:$H$1001,C$4) -> 34 | D8: =COUNTIFS('Word List'!$G$2:$G$1001,$A8,'Word List'!$H$2:$H$1001,D$4) -> 18 | E8: =COUNTIFS('Word List'!$G$2:$G$1001,$A8,'Word List'!$H$2:$H$1001,E$4) -> 2 | F8: =SUM(B8:E8) -> 69
A9: Faith & Religion | B9: =COUNTIFS('Word List'!$G$2:$G$1001,$A9,'Word List'!$H$2:$H$1001,B$4) -> 0 | C9: =COUNTIFS('Word List'!$G$2:$G$1001,$A9,'Word List'!$H$2:$H$1001,C$4) -> 7 | D9: =COUNTIFS('Word List'!$G$2:$G$1001,$A9,'Word List'!$H$2:$H$1001,D$4) -> 11 | E9: =COUNTIFS('Word List'!$G$2:$G$1001,$A9,'Word List'!$H$2:$H$1001,E$4) -> 2 | F9: =SUM(B9:E9) -> 20
A10: Feelings & Values | B10: =COUNTIFS('Word List'!$G$2:$G$1001,$A10,'Word List'!$H$2:$H$1001,B$4) -> 9 | C10: =COUNTIFS('Word List'!$G$2:$G$1001,$A10,'Word List'!$H$2:$H$1001,C$4) -> 16 | D10: =COUNTIFS('Word List'!$G$2:$G$1001,$A10,'Word List'!$H$2:$H$1001,D$4) -> 7 | E10: =COUNTIFS('Word List'!$G$2:$G$1001,$A10,'Word List'!$H$2:$H$1001,E$4) -> 0 | F10: =SUM(B10:E10) -> 32
A11: Food & Drink | B11: =COUNTIFS('Word List'!$G$2:$G$1001,$A11,'Word List'!$H$2:$H$1001,B$4) -> 3 | C11: =COUNTIFS('Word List'!$G$2:$G$1001,$A11,'Word List'!$H$2:$H$1001,C$4) -> 3 | D11: =COUNTIFS('Word List'!$G$2:$G$1001,$A11,'Word List'!$H$2:$H$1001,D$4) -> 1 | E11: =COUNTIFS('Word List'!$G$2:$G$1001,$A11,'Word List'!$H$2:$H$1001,E$4) -> 0 | F11: =SUM(B11:E11) -> 7
A12: Grammar Essentials | B12: =COUNTIFS('Word List'!$G$2:$G$1001,$A12,'Word List'!$H$2:$H$1001,B$4) -> 49 | C12: =COUNTIFS('Word List'!$G$2:$G$1001,$A12,'Word List'!$H$2:$H$1001,C$4) -> 101 | D12: =COUNTIFS('Word List'!$G$2:$G$1001,$A12,'Word List'!$H$2:$H$1001,D$4) -> 129 | E12: =COUNTIFS('Word List'!$G$2:$G$1001,$A12,'Word List'!$H$2:$H$1001,E$4) -> 6 | F12: =SUM(B12:E12) -> 285
A13: Home & Everyday Life | B13: =COUNTIFS('Word List'!$G$2:$G$1001,$A13,'Word List'!$H$2:$H$1001,B$4) -> 5 | C13: =COUNTIFS('Word List'!$G$2:$G$1001,$A13,'Word List'!$H$2:$H$1001,C$4) -> 8 | D13: =COUNTIFS('Word List'!$G$2:$G$1001,$A13,'Word List'!$H$2:$H$1001,D$4) -> 2 | E13: =COUNTIFS('Word List'!$G$2:$G$1001,$A13,'Word List'!$H$2:$H$1001,E$4) -> 2 | F13: =SUM(B13:E13) -> 17
A14: Law & Courts | B14: =COUNTIFS('Word List'!$G$2:$G$1001,$A14,'Word List'!$H$2:$H$1001,B$4) -> 0 | C14: =COUNTIFS('Word List'!$G$2:$G$1001,$A14,'Word List'!$H$2:$H$1001,C$4) -> 0 | D14: =COUNTIFS('Word List'!$G$2:$G$1001,$A14,'Word List'!$H$2:$H$1001,D$4) -> 2 | E14: =COUNTIFS('Word List'!$G$2:$G$1001,$A14,'Word List'!$H$2:$H$1001,E$4) -> 27 | F14: =SUM(B14:E14) -> 29
A15: Names | B15: =COUNTIFS('Word List'!$G$2:$G$1001,$A15,'Word List'!$H$2:$H$1001,B$4) -> 0 | C15: =COUNTIFS('Word List'!$G$2:$G$1001,$A15,'Word List'!$H$2:$H$1001,C$4) -> 0 | D15: =COUNTIFS('Word List'!$G$2:$G$1001,$A15,'Word List'!$H$2:$H$1001,D$4) -> 0 | E15: =COUNTIFS('Word List'!$G$2:$G$1001,$A15,'Word List'!$H$2:$H$1001,E$4) -> 22 | F15: =SUM(B15:E15) -> 22
A16: Nature & Animals | B16: =COUNTIFS('Word List'!$G$2:$G$1001,$A16,'Word List'!$H$2:$H$1001,B$4) -> 3 | C16: =COUNTIFS('Word List'!$G$2:$G$1001,$A16,'Word List'!$H$2:$H$1001,C$4) -> 8 | D16: =COUNTIFS('Word List'!$G$2:$G$1001,$A16,'Word List'!$H$2:$H$1001,D$4) -> 2 | E16: =COUNTIFS('Word List'!$G$2:$G$1001,$A16,'Word List'!$H$2:$H$1001,E$4) -> 0 | F16: =SUM(B16:E16) -> 13
... A25: Work & Money | B25: =COUNTIFS('Word List'!$G$2:$G$1001,$A25,'Word List'!$H$2:$H$1001,B$4) -> 1 | C25: =COUNTIFS('Word List'!$G$2:$G$1001,$A25,'Word List'!$H$2:$H$1001,C$4) -> 4 | D25: =COUNTIFS('Word List'!$G$2:$G$1001,$A25,'Word List'!$H$2:$H$1001,D$4) -> 11 | E25: =COUNTIFS('Word List'!$G$2:$G$1001,$A25,'Word List'!$H$2:$H$1001,E$4) -> 3 | F25: =SUM(B25:E25) -> 19
A26: Total | B26: =SUM(B5:B25) -> 182 | C26: =SUM(C5:C25) -> 341 | D26: =SUM(D5:D25) -> 367 | E26: =SUM(E5:E25) -> 110 | F26: =SUM(F5:F25) -> 1000
A28: Words marked "Check" | B28: =COUNTIF('Word List'!$M$2:$M$1001,"Check") -> 7
A29: Starter Words listed | B29: =COUNTA('Starter Words'!$B$5:$B$186) -> 182
